khan_api_wrapper/__init__.py
khan_api_wrapper/graphql_schema.py
khan_api_wrapper/khan.py
khan_api_wrapper-0.0.18.dist-info/LICENSE
khan_api_wrapper-0.0.18.dist-info/METADATA
khan_api_wrapper-0.0.18.dist-info/WHEEL
khan_api_wrapper-0.0.18.dist-info/top_level.txt
khan_api_wrapper-0.0.18.dist-info/RECORD
