Metadata-Version: 2.1
Name: khan-api-wrapper
Version: 0.0.18
Summary: Simple, direct Python 3 wrapper for the Khan Academy API
Home-page: https://github.com/jb-1980/khan_api_wrapper
Author: Joseph Gilgen
Author-email: gilgenlabs@gmail.com
License: UNKNOWN
Platform: UNKNOWN
Classifier: Programming Language :: Python :: 3
Classifier: License :: OSI Approved :: MIT License
Classifier: Operating System :: OS Independent
Requires-Dist: requests
Requires-Dist: rauth (>=0.7.3)
